inmanta_plugins/web/__init__.py
inmanta_plugins/web/setup.cfg
inmanta_plugins/web/model/_init.cf
inmanta_module_web-0.3.20.dist-info/METADATA
inmanta_module_web-0.3.20.dist-info/WHEEL
inmanta_module_web-0.3.20.dist-info/top_level.txt
inmanta_module_web-0.3.20.dist-info/RECORD
