Metadata-Version: 2.1
Name: inmanta-module-web
Version: 0.3.20
License: Apache 2.0
Requires-Dist: inmanta-module-ip
Requires-Dist: inmanta-module-std
